{
  "users": [
    {
      "username": "user1",
      "password": "123",
      "gameInProgress": true,
      "scene": "3",
      "lives": "0",
      "score": "5",
      "musicOn": "False",
      "volume": "0.5",
      "topScore": 100
    },
    {
      "username": "user2",
      "password": 123,
      "gameInProgress": false,
      "scene": 6,
      "lives": 1,
      "score": 75,
      "musicOn": false,
      "volume": 0,
      "topScore": 75
    },
    {
      "username": "gracie",
      "password": "123",
      "gameInProgress": false,
      "scene": "3",
      "lives": "5",
      "score": "0",
      "musicOn": "True",
      "volume": "0.5",
      "topScore": 0
    }
  ]
}